{
"shabadhazareGurmukhi":
 [
{"Gurmukhi": "Sbd_hjwry"},
{"Gurmukhi": "<font color='#009900'>mwJ </font> mhlw <font color='#FFA500'>5 </font><font color='#009900'>caupdy </font> Gru 1]"},
{"Gurmukhi": "myrw mnu <font color='#FFA500'>locY </font> gur drsn qweI ]"},
{"Gurmukhi": "iblp <font color='#FFA500'>kry </font> cwiqRk kI inAweI ]"},
{"Gurmukhi": "iqRKw n <font color='#009900'>auqrY </font> sWiq n <font color='#FFA500'>AwvY </font> ibnu drsn sMq ipAwry jIau ]1]"},
{"Gurmukhi": "hau <font color='#009900'>GolI </font> jIau Goil <font color='#FFA500'>GumweI </font> gur drsn sMq ipAwry jIau ]1] rhwau ]"},
{"Gurmukhi": "qyrw muKu suhwvw <font color='#FFA500'>jIau </font> shj Duin bwxI ]"},
{"Gurmukhi": "icru <font color='#FFA500'>hoAw </font> dyKy swirMgpwxI ]"},
{"Gurmukhi": "DMnu su <font color='#009900'>dysu </font> jhw qUM <font color='#FFA500'>visAw </font> myry sjx mIq murwry jIau ]2]"},
{"Gurmukhi": "hau <font color='#009900'>GolI </font> hau Goil <font color='#FFA500'>GumweI </font>  gur sjx mIq murwry jIau ]1] rhwau ]"},
{"Gurmukhi": "iek GVI n <font color='#FFA500'>imlqy </font> qw kiljugu hoqw ]"},
{"Gurmukhi": "huix kid <font color='#FFA500'>imlIAY </font> ipRA quDu BgvMqw ]"},
{"Gurmukhi": "moih rYix n <font color='#009900'>ivhwvY </font> nId n <font color='#FFA500'>AwvY </font> ibnu dyKy gur drbwry jIau ]3]"},
{"Gurmukhi": "hau <font color='#009900'>GolI </font> jIau Goil <font color='#FFA500'>GumweI </font> iqsu scy gur drbwry jIau ]1] rhwau ]"},
{"Gurmukhi": "Bwgu <font color='#FFA500'>hoAw </font> guir sMqu imlwieAw ]"},
{"Gurmukhi": "pRBu <font color='#FFA500'>AibnwsI </font> Gr mih pwieAw ]"},
{"Gurmukhi": "syv <font color='#009900'>krI </font> plu csw n <font color='#FFA500'>ivCuVw </font> jn nwnk dws qumwry jIau ]4]"},
{"Gurmukhi": "hau <font color='#009900'>GolI </font> jIau Goil <font color='#FFA500'>GumweI </font> jn nwnk dws qumwry jIau ] rhwau ]1]8]"},
{"Gurmukhi": "<font color='#009900'>DnwsrI </font> mhlw <font color='#FFA500'>1 </font> Gru <font color='#009900'>1 </font> caupdy"},
{"Gurmukhi": "<font color='#FFA500'>&lt;&gt; </font><font color='#009900'>siqnwmu </font> krqw <font color='#009900'>purK</font><font color='#009900'>u</font> inrBau <font color='#FFA500'>inrvYru </font>  Akwl <font color='#009900'>mUriq </font> AjUnI <font color='#009900'>sYB</font><font color='#009900'>M</font> gurpRswid ]"},
{"Gurmukhi": "jIau frqu hY <font color='#FFA500'>Awpxw </font> kY isau krI pukwr ]"},
{"Gurmukhi": "dUK ivswrxu <font color='#FFA500'>syivAw </font> sdw sdw dwqwru ]1]"},
{"Gurmukhi": "swihbu myrw nIq <font color='#FFA500'>nvw </font> sdw sdw dwqwru ]1] rhwau ]"},
{"Gurmukhi": "Anidnu swihbu <font color='#FFA500'>syvIAY </font> AMiq Cfwey soie ]"},
{"Gurmukhi": "suix suix myrI <font color='#FFA500'>kwmxI </font> pwir auqwrw hoie ]2]"},
{"Gurmukhi": "<font color='#FFA500'>dieAwl </font> qyrY nwim qrw ]"},
{"Gurmukhi": "<font color='#FFA500'>sd </font> kurbwxY jwau ]1] rhwau ]"},
{"Gurmukhi": "srbM swcw eyku <font color='#FFA500'>hY </font> dUjw nwhI koie ]"},
{"Gurmukhi": "qw  kI syvw so <font color='#FFA500'>kry </font> jw kau ndir kry ]3]"},
{"Gurmukhi": "quDu bwJu <font color='#FFA500'>ipAwry </font> kyv rhw ]"},
{"Gurmukhi": "sw vifAweI <font color='#FFA500'> dyih </font> ijqu nwim qyry lwig rhW ]"},
{"Gurmukhi": "dUjw nwhI <font color='#FFA500'>koie </font> ijsu AwgY ipAwry jwie khw ]1] rhwau ]"},
{"Gurmukhi": "syvI swihbu <font color='#FFA500'>Awpxw </font> Avru n jwcMau koie ]"},
{"Gurmukhi": "nwnku qw kw dwsu <font color='#FFA500'>hY </font> ibMd ibMd cuK cuK hoie ]4]"},
{"Gurmukhi": "swihb qyry nwm <font color='#FFA500'>ivthu </font> ibMd ibMd cuK cuK hoie ]1] rhwau ]4]1]"},
{"Gurmukhi": "<font color='#009900'>iqlMg </font> mhlw <font color='#FFA500'>1 </font> Gru 3<font color='#FFA500'>&lt;&gt; </font> siqgur pRswid ]"},
{"Gurmukhi": "iehu qnu mwieAw pwihAw <font color='#FFA500'>ipAwry </font>  lIqVw lib rMgwey ]"},
{"Gurmukhi": "myrY kMq n BwvY colVw <font color='#FFA500'>ipAwry </font> ikau Dn syjY jwey ]1]"},
{"Gurmukhi": "hMau kurbwnY jwau <font color='#FFA500'>imhrvwnw </font> hMau kurbwnY jwau ]"},
{"Gurmukhi": "hMau kurbwnY jwau iqnw <font color='#FFA500'>kY </font> lYn jo qyrw nwau ]"},
{"Gurmukhi": "lYin jo qyrw <font color='#009900'>nwau </font> iqnw <font color='#FFA500'>kY </font> hMau sd kurbwnY jwau ]1] rhwau ]"},
{"Gurmukhi": "kwieAw rM|ix jy QIAY <font color='#FFA500'>ipAwry </font> pweIAY nwau mjIT ]"},
{"Gurmukhi": "rM|x <font color='#009900'>vwlw </font> jy rM|Y <font color='#FFA500'>swihbu </font> AYsw rMgu n fIT ]2]"},
{"Gurmukhi": "ijn ky coly rqVy <font color='#FFA500'>ipAwry </font> kMqu iqnw kY pwis ]"},
{"Gurmukhi": "DUiV iqnw kI jy <font color='#009900'>imlY </font> jI <font color='#FFA500'>khu </font> nwnk kI Ardwis ]3]"},
{"Gurmukhi": "Awpy swjy Awpy <font color='#FFA500'>rMgy </font> Awpy ndir kryie ]"},
{"Gurmukhi": "<font color='#009900'>nwnk </font> kwmix kMqY <font color='#FFA500'>BwvY </font> Awpy hI rwvyie ]4]1]3]"},
{"Gurmukhi": "<font color='#009900'>iqlMg </font> mÚ 1]"},
{"Gurmukhi": "<font color='#FFA500'>ieAwnVIey </font> mwnVw kwie kryih ]"},
{"Gurmukhi": "AwpnVY Gir <font color='#FFA500'>hir </font> rMgo kI n mwxyih ]"},
{"Gurmukhi": "shu nyVY Dn <font color='#FFA500'>kMmlIey </font> bwhru ikAw FUFyih ]"},
{"Gurmukhi": "BY kIAw dyih slweIAw <font color='#FFA500'>nYxI </font> Bwv kw kir sIgwro ]"},
{"Gurmukhi": "qw sohwgix jwxIAY <font color='#FFA500'>lwgI </font> jw shu Dry ipAwro ]1]"},
{"Gurmukhi": "ieAwxI bwlI ikAw <font color='#FFA500'>kry </font> jw Dn kMq n BwvY ]"},
{"Gurmukhi": "krx plwh kry <font color='#FFA500'>bhuqyry </font> sw Dn mhlu n pwvY ]"},
{"Gurmukhi": "ivxu krmw ikCu pweIAY <font color='#FFA500'>nwhI </font> jy bhuqyrw DwvY ]"},
{"Gurmukhi": "lb loB AhMkwr kI <font color='#FFA500'>mwqI </font> mwieAw mwih smwxI ]"},
{"Gurmukhi": "ienI bwqI shu pweIAY <font color='#FFA500'>nwhI </font> BeI kwmix ieAwxI ]2]"},
{"Gurmukhi": "jwie puChu  sohwgxI <font color='#FFA500'>vwhY </font> iknI bwqI shu pweIAY ]"},
{"Gurmukhi": "jo ikCu kry so Blw kir <font color='#FFA500'>mwnIAY </font> ihkmiq hukmu cukweIAY ]"},
{"Gurmukhi": "jw kY pRyim pdwrQu <font color='#FFA500'>pweIAY </font> qau crxI icqu lweIAY ]"},
{"Gurmukhi": "shu khY so <font color='#009900'>kIjY </font> qnu mno <font color='#FFA500'>dIjY </font> AYsw prmlu lweIAY ]"},
{"Gurmukhi": "eyv khih sohwgxI <font color='#FFA500'>BYxy </font> ienI bwqI shu pweIAY ]3]"},
{"Gurmukhi": "Awpu <font color='#009900'>gvweIAY </font> qw shu <font color='#FFA500'>pweIAY </font> Aauru kYsI cqurweI ]"},
{"Gurmukhi": "shu ndir kir <font color='#009900'>dyKY </font> so idnu <font color='#FFA500'>lyKY </font> kwmix nau iniD pweI ]"},
{"Gurmukhi": "Awpxy kMq <font color='#009900'>ipAwrI </font> sw <font color='#FFA500'>sohwgix </font> nwnk sw sBrweI ]"},
{"Gurmukhi": "AYsY rMig <font color='#009900'>rwqI </font> shj kI <font color='#FFA500'>mwqI </font> Aihinis Bwie smwxI ]"},
{"Gurmukhi": "suMdir swie srUp  <font color='#FFA500'>ibcKix </font> khIAY sw isAwxI ]4]2]4]"},
{"Gurmukhi": "<font color='#009900'>sUhI </font> mhlw 1]"},
{"Gurmukhi": "kaux qrwjI kvxu <font color='#FFA500'>qulw </font> qyrw kvxu srwPu bulwvw ]"},
{"Gurmukhi": "kauxu gurU kY pih dIiKAw <font color='#FFA500'>lyvw </font> kY pih mulu krwvw ]1]"},
{"Gurmukhi": "myry lwl <font color='#FFA500'>jIau </font> qyrw AMqu n jwxw ]"},
{"Gurmukhi": "qUM jil Qil mhIAil Birpuir <font color='#FFA500'>lIxw </font> qUM Awpy srb smwxw ]1] rhwau ]"},
{"Gurmukhi": "mnu <font color='#009900'>qwrwjI </font> icqu <font color='#FFA500'>qulw </font> qyrI syv srwPu kmwvw ]"},
{"Gurmukhi": "Gt hI BIqir so shu <font color='#FFA500'>qolI </font> ien@ ibiD icqu rhwvw ]2]"},
{"Gurmukhi": "Awpy kMfw qolu <font color='#FFA500'>qrwjI </font> Awpy qolxhwrw ]"},
{"Gurmukhi": "Awpy dyKY Awpy <font color='#FFA500'>bUJY </font> Awpy hY vxjwrw ] 3]"},
{"Gurmukhi": "<font color='#009900'>AMDulw </font> nIc <font color='#009900'>jwiq </font><font color='#FFA500'>prdysI </font> iKnu AwvY iqlu jwvY ]"},
{"Gurmukhi": "qw kI <font color='#009900'>sMgiq </font> nwnku <font color='#FFA500'>rhdw </font> ikau kir mUVw pwvY ]4]2]9]"},
{"Gurmukhi": "<font color='#FFA500'>&lt;&gt; </font><font color='#009900'>siqnwmu </font> krqw <font color='#009900'>purKu </font> inrBau <font color='#FFA500'>inrvYru </font> Akwl <font color='#009900'>mUriq </font> AjUnI <font color='#009900'>sYBM </font> gurpRswid ]"},
{"Gurmukhi": "rwgu <font color='#009900'>iblwvlu </font> mhlw <font color='#FFA500'>1 </font><font color='#009900'>caupdy </font> Gru 1 ]"},
{"Gurmukhi": "qU <font color='#009900'>sulqwnu </font> khw hau <font color='#FFA500'>mIAw </font> qyrI kvn vfweI ]"},
{"Gurmukhi": "jo qU dyih su khw <font color='#FFA500'>suAwmI </font> mY mUrK khxu n jweI ]1]"},
{"Gurmukhi": "qyry gux  <font color='#FFA500'>gwvw </font> dyih buJweI ]"},
{"Gurmukhi": "jYsy sc mih <font color='#FFA500'>rhau </font> rjweI ]1] rhwau ]"},
{"Gurmukhi": "jo ikCu <font color='#009900'>hoAw </font> sBu ikCu quJ <font color='#FFA500'>qy </font> qyrI sB AsnweI ]"},
{"Gurmukhi": "qyrw AMqu n jwxw myry <font color='#FFA500'>swihb </font> mY AMDuly ikAw cqurweI ]2]"},
{"Gurmukhi": "ikAw hau <font color='#009900'>kQI </font> kQy kiQ <font color='#FFA500'>dyKw </font><font color='#009900'>mY </font> AkQu n kQnw jweI ]"},
{"Gurmukhi": "jo quDu BwvY soeI <font color='#FFA500'>AwKw </font> iqlu qyrI vifAweI ]3]"},
{"Gurmukhi": "eyqy <font color='#009900'>kUkr </font> hau <font color='#FFA500'>bygwnw </font> Baukw iesu qn qweI ]"},
{"Gurmukhi": "Bgiq hIxu nwnku jy <font color='#FFA500'>hoiegw </font> qw KsmY nwau n jweI ]4]1]"},
{"Gurmukhi": "<font color='#009900'>iblwvlu </font> mhlw 1]"},
{"Gurmukhi": "mnu mMdru qnu vys <font color='#FFA500'>klMdru </font> Gt hI qIriQ nwvw ]"},
{"Gurmukhi": "eyku sbdu myrY pRwin  bsqu <font color='#FFA500'>hY </font> bwhuiV jnim n Awvw ]1]"},
{"Gurmukhi": "mnu <font color='#009900'>byiDAw </font> dieAwl <font color='#FFA500'>syqI </font> myrI mweI ]"},
{"Gurmukhi": "kauxu <font color='#FFA500'>jwxY </font> pIr prweI ]"},
{"Gurmukhi": "hm <font color='#FFA500'>nwhI </font> icMq prweI ]1] rhwau ]"},
{"Gurmukhi": "Agm Agocr AlK <font color='#FFA500'>Apwrw </font> icMqw krhu hmwrI ]"},
{"Gurmukhi": "jil Qil mhIAil Birpuir <font color='#FFA500'>lIxw </font> Git Git joiq qumwrI ]2]"},
{"Gurmukhi": "isK miq sB buiD <font color='#FFA500'>qum@wrI </font> mMidr Cwvw qyry ]"},
{"Gurmukhi": "quJ ibnu Avru n jwxw myry <font color='#FFA500'>swihbw </font> gux gwvw inq qyry ]3]"},
{"Gurmukhi": "jIA jMq siB srix <font color='#FFA500'>qum@wrI </font> srb icMq quDu pwsy ]"},
{"Gurmukhi": "jo quDu BwvY soeI <font color='#FFA500'>cMgw </font> iek nwnk kI Ardwsy ]4]2]"}
]
}
